pnt_functional/__init__.py
pnt_functional/main.py
pnt_functional/tests/test_main.py
pnt_functional-0.1.1.dist-info/METADATA
pnt_functional-0.1.1.dist-info/WHEEL
pnt_functional-0.1.1.dist-info/entry_points.txt
pnt_functional-0.1.1.dist-info/RECORD
