Metadata-Version: 2.4
Name: pnt-functional
Version: 0.1.1
Summary: A Python package template using Nix and uv
Author-email: Your Name <your.email@example.com>
License: Apache-2.0
Classifier: Development Status :: 3 - Alpha
Classifier: License :: OSI Approved :: MIT License
Classifier: Operating System :: OS Independent
Classifier: Programming Language :: Python :: 3
Classifier: Programming Language :: Python :: 3.11
Classifier: Programming Language :: Python :: 3.12
Requires-Python: <3.13,>=3.11
Requires-Dist: beartype<0.20.0,>=0.19.0
Requires-Dist: expression>=5.5.0
